asmbly_neon_integrations/AsmblyMessageFactory.py
asmbly_neon_integrations/__init__.py
asmbly_neon_integrations/credentials.py
asmbly_neon_integrations/flodeskUtil.py
asmbly_neon_integrations/gmailUtil.py
asmbly_neon_integrations/helpers/api.py
asmbly_neon_integrations/helpers/gmail.py
asmbly_neon_integrations/helpers/neon.py
asmbly_neon_integrations/mailjetUtil.py
asmbly_neon_integrations/neonUtil.py
asmbly_neon_integrations/openPathPruneUsers.py
asmbly_neon_integrations/openPathUpdateAll.py
asmbly_neon_integrations/openPathUpdateSingle.py
asmbly_neon_integrations/openPathUtil.py
asmbly_neon_integrations/request_backoff.py
asmbly_neon_integrations-0.1.13.dist-info/METADATA
asmbly_neon_integrations-0.1.13.dist-info/WHEEL
asmbly_neon_integrations-0.1.13.dist-info/RECORD
