Metadata-Version: 2.1
Name: asmbly-neon-integrations
Version: 0.1.13
Summary: Various convenience functions and scripts for managing integrations at Asmbly Makerspace.
License: GPL-3.0-or-later
Author: Matthew Miller
Author-email: matthew.miller@asmbly.org
Requires-Python: >=3.9
Classifier: License :: OSI Approved :: GNU General Public License v3 or later (GPLv3+)
Classifier: Programming Language :: Python :: 3
Classifier: Programming Language :: Python :: 3.9
Classifier: Programming Language :: Python :: 3.10
Classifier: Programming Language :: Python :: 3.11
Classifier: Programming Language :: Python :: 3.12
Requires-Dist: aiohttp (>=3.9.5,<4.0.0)
Requires-Dist: boto3 (>=1.35.47,<2.0.0)
Requires-Dist: mailjet-rest (>=1.3.4,<2.0.0)
Requires-Dist: pydantic (>=2.9.2,<3.0.0)
Requires-Dist: pytz (>=2024.1,<2025.0)
Requires-Dist: requests (>=2.32.3,<3.0.0)
